randompasswords/InputFrame.py
randompasswords/InputValidator.py
randompasswords/__init__.py
randompasswords/__main__.py
randompasswords/passwordgenerator.py
randompasswords-2.0.0.dist-info/METADATA
randompasswords-2.0.0.dist-info/WHEEL
randompasswords-2.0.0.dist-info/top_level.txt
randompasswords-2.0.0.dist-info/RECORD
