Metadata-Version: 2.1
Name: randompasswords
Version: 2.0.0
Summary: Takes user input and generates random passwords
Home-page: https://github.com/JosephJ12/randompasswords
Author: Joseph Jung
Author-email: josephjung12@gmail.com
License: MIT
Platform: UNKNOWN
Classifier: License :: OSI Approved :: MIT License
Classifier: Programming Language :: Python :: 3
Classifier: Programming Language :: Python :: 3.7
